{
    "checksum": "4f20e25dc988c05b6e65c3792f116332",
    "wallpaper": "/home/suku/wallpaper/winter_car.jpg",
    "alpha": "100",
    "special": {
        "background": "#000104",
        "foreground": "#bfbfc0",
        "cursor": "#bfbfc0"
    },
    "colors": {
        "color0": "#000104",
        "color1": "#184770",
        "color2": "#294C70",
        "color3": "#4B4369",
        "color4": "#285B88",
        "color5": "#306798",
        "color6": "#4775A4",
        "color7": "#bfbfc0",
        "color8": "#3f4042",
        "color9": "#184770",
        "color10": "#294C70",
        "color11": "#4B4369",
        "color12": "#285B88",
        "color13": "#306798",
        "color14": "#4775A4",
        "color15": "#bfbfc0"
    }
}